ebk/__init__.py
ebk/calibre_import.py
ebk/cli.py
ebk/config.py
ebk/decorators.py
ebk/extract_metadata.py
ebk/ident.py
ebk/library_db.py
ebk/opds.py
ebk/search_parser.py
ebk/server.py
ebk/vfs_router.py
ebk/ai/__init__.py
ebk/ai/knowledge_graph.py
ebk/ai/metadata_enrichment.py
ebk/ai/question_generator.py
ebk/ai/reading_companion.py
ebk/ai/semantic_search.py
ebk/ai/text_extractor.py
ebk/ai/llm_providers/__init__.py
ebk/ai/llm_providers/anthropic.py
ebk/ai/llm_providers/base.py
ebk/ai/llm_providers/gemini.py
ebk/ai/llm_providers/ollama.py
ebk/db/__init__.py
ebk/db/migrations.py
ebk/db/models.py
ebk/db/session.py
ebk/exports/__init__.py
ebk/exports/base_exporter.py
ebk/exports/echo_export.py
ebk/exports/html_library.py
ebk/exports/html_utils.py
ebk/exports/hugo.py
ebk/exports/jinja_export.py
ebk/exports/multi_facet_export.py
ebk/exports/opds_export.py
ebk/exports/symlink_dag.py
ebk/exports/zip.py
ebk/plugins/__init__.py
ebk/plugins/base.py
ebk/plugins/hooks.py
ebk/plugins/registry.py
ebk/repl/__init__.py
ebk/repl/find.py
ebk/repl/grep.py
ebk/repl/shell.py
ebk/repl/text_utils.py
ebk/services/__init__.py
ebk/services/annotation_extraction.py
ebk/services/annotation_service.py
ebk/services/export_service.py
ebk/services/import_service.py
ebk/services/personal_metadata_service.py
ebk/services/queue_service.py
ebk/services/tag_service.py
ebk/services/text_extraction.py
ebk/services/view_service.py
ebk/similarity/__init__.py
ebk/similarity/base.py
ebk/similarity/core.py
ebk/similarity/extractors.py
ebk/similarity/metrics.py
ebk/skills/SKILL.md
ebk/skills/__init__.py
ebk/vfs/__init__.py
ebk/vfs/base.py
ebk/vfs/library_vfs.py
ebk/vfs/resolver.py
ebk/vfs/nodes/__init__.py
ebk/vfs/nodes/authors.py
ebk/vfs/nodes/books.py
ebk/vfs/nodes/files.py
ebk/vfs/nodes/metadata.py
ebk/vfs/nodes/root.py
ebk/vfs/nodes/similar.py
ebk/vfs/nodes/subjects.py
ebk/vfs/nodes/tags.py
ebk/views/__init__.py
ebk/views/dsl.py
ebk/views/service.py
ebk-0.4.4.dist-info/licenses/LICENSE
ebk-0.4.4.dist-info/METADATA
ebk-0.4.4.dist-info/WHEEL
ebk-0.4.4.dist-info/entry_points.txt
ebk-0.4.4.dist-info/top_level.txt
ebk-0.4.4.dist-info/RECORD
