Metadata-Version: 2.4
Name: ebk
Version: 0.4.4
Summary: A lightweight, extensible tool for managing eBook metadata
Home-page: https://github.com/queelius/ebk
Author: Alex Towell
Author-email: Alex Towell <lex@metafunctor.com>
Maintainer-email: Alex Towell <lex@metafunctor.com>
License: MIT
Project-URL: Homepage, https://github.com/queelius/ebk
Project-URL: Documentation, https://github.com/queelius/ebk/wiki
Project-URL: Repository, https://github.com/queelius/ebk.git
Project-URL: Issues, https://github.com/queelius/ebk/issues
Project-URL: Changelog, https://github.com/queelius/ebk/blob/main/CHANGELOG.md
Keywords: ebook,metadata,library,books,management,calibre
Classifier: Development Status :: 4 - Beta
Classifier: Intended Audience :: End Users/Desktop
Classifier: Intended Audience :: Developers
Classifier: License :: OSI Approved :: MIT License
Classifier: Programming Language :: Python :: 3
Classifier: Programming Language :: Python :: 3.10
Classifier: Programming Language :: Python :: 3.11
Classifier: Programming Language :: Python :: 3.12
Classifier: Topic :: Software Development :: Libraries
Classifier: Topic :: Text Processing :: Markup
Classifier: Topic :: Utilities
Requires-Python: >=3.8
License-File: LICENSE
Requires-Dist: typer>=0.9.0
Requires-Dist: rich>=13.0.0
Requires-Dist: lxml>=4.9.0
Requires-Dist: python-slugify>=8.0.0
Requires-Dist: pyyaml>=6.0
Requires-Dist: pypdf>=3.0.0
Requires-Dist: PyMuPDF>=1.23.0
Requires-Dist: ebooklib>=0.18
Requires-Dist: Pillow>=10.0.0
Requires-Dist: jmespath>=1.0.0
Requires-Dist: jinja2>=3.0.0
Requires-Dist: xmltodict>=0.13.0
Provides-Extra: ai
Requires-Dist: sentence-transformers>=2.2.0; extra == "ai"
Requires-Dist: scikit-learn>=1.3.0; extra == "ai"
Requires-Dist: networkx>=3.0; extra == "ai"
Requires-Dist: beautifulsoup4>=4.12.0; extra == "ai"
Requires-Dist: numpy>=1.24.0; extra == "ai"
Provides-Extra: streamlit
Requires-Dist: streamlit>=1.28.0; extra == "streamlit"
Requires-Dist: pandas>=2.0.0; extra == "streamlit"
Requires-Dist: altair>=5.0.0; extra == "streamlit"
Provides-Extra: metadata
Requires-Dist: aiohttp>=3.8.0; extra == "metadata"
Requires-Dist: beautifulsoup4>=4.12.0; extra == "metadata"
Requires-Dist: httpx>=0.24.0; extra == "metadata"
Provides-Extra: google-books
Requires-Dist: aiohttp>=3.8.0; extra == "google-books"
Provides-Extra: network
Provides-Extra: network-advanced
Requires-Dist: networkx>=3.0; extra == "network-advanced"
Requires-Dist: matplotlib>=3.5.0; extra == "network-advanced"
Requires-Dist: pyvis>=0.3.0; extra == "network-advanced"
Requires-Dist: plotly>=5.0.0; extra == "network-advanced"
Provides-Extra: llm
Requires-Dist: httpx>=0.24.0; extra == "llm"
Requires-Dist: pydantic>=2.0.0; extra == "llm"
Provides-Extra: mcp
Requires-Dist: mcp>=0.1.0; extra == "mcp"
Requires-Dist: pydantic>=2.0.0; extra == "mcp"
Provides-Extra: dev
Requires-Dist: pytest>=7.0.0; extra == "dev"
Requires-Dist: pytest-asyncio>=0.21.0; extra == "dev"
Requires-Dist: pytest-cov>=4.0.0; extra == "dev"
Requires-Dist: black>=23.0.0; extra == "dev"
Requires-Dist: ruff>=0.1.0; extra == "dev"
Requires-Dist: mypy>=1.0.0; extra == "dev"
Requires-Dist: pre-commit>=3.0.0; extra == "dev"
Provides-Extra: docs
Requires-Dist: mkdocs>=1.5.0; extra == "docs"
Requires-Dist: mkdocs-material>=9.0.0; extra == "docs"
Requires-Dist: mkdocstrings[python]>=0.24.0; extra == "docs"
Provides-Extra: all
Requires-Dist: sentence-transformers>=2.2.0; extra == "all"
Requires-Dist: scikit-learn>=1.3.0; extra == "all"
Requires-Dist: streamlit>=1.28.0; extra == "all"
Requires-Dist: pandas>=2.0.0; extra == "all"
Requires-Dist: altair>=5.0.0; extra == "all"
Requires-Dist: aiohttp>=3.8.0; extra == "all"
Requires-Dist: beautifulsoup4>=4.12.0; extra == "all"
Requires-Dist: httpx>=0.24.0; extra == "all"
Requires-Dist: networkx>=3.0; extra == "all"
Requires-Dist: matplotlib>=3.5.0; extra == "all"
Requires-Dist: pyvis>=0.3.0; extra == "all"
Requires-Dist: plotly>=5.0.0; extra == "all"
Requires-Dist: numpy>=1.24.0; extra == "all"
Provides-Extra: viz
Requires-Dist: ebk[network-advanced]; extra == "viz"
Dynamic: author
Dynamic: home-page
Dynamic: license-file
Dynamic: requires-python
